<annotation>
	<folder>entrenamiento</folder>
	<filename>img_2023-08-11.jpg</filename>
	<path>C:\Users\Luis\Desktop\Maestria\Teledeteccion\Bases de datos\Imagenes satelitales\entrenamiento\img_2023-08-11.jpg</path>
	<source>
		<database>Unknown</database>
	</source>
	<size>
		<width>985</width>
		<height>1108</height>
		<depth>3</depth>
	</size>
	<segmented>0</segmented>
	<object>
		<name>precipitacion</name>
		<pose>Unspecified</pose>
		<truncated>1</truncated>
		<difficult>0</difficult>
		<bndbox>
			<xmin>750</xmin>
			<ymin>638</ymin>
			<xmax>985</xmax>
			<ymax>845</ymax>
		</bndbox>
	</object>
	<object>
		<name>precipitacion</name>
		<pose>Unspecified</pose>
		<truncated>1</truncated>
		<difficult>0</difficult>
		<bndbox>
			<xmin>1</xmin>
			<ymin>1005</ymin>
			<xmax>119</xmax>
			<ymax>1066</ymax>
		</bndbox>
	</object>
	<object>
		<name>precipitacion</name>
		<pose>Unspecified</pose>
		<truncated>0</truncated>
		<difficult>0</difficult>
		<bndbox>
			<xmin>401</xmin>
			<ymin>280</ymin>
			<xmax>474</xmax>
			<ymax>344</ymax>
		</bndbox>
	</object>
</annotation>
